aioslimproto/__init__.py
aioslimproto/cli.py
aioslimproto/client.py
aioslimproto/const.py
aioslimproto/discovery.py
aioslimproto/display.py
aioslimproto/errors.py
aioslimproto/models.py
aioslimproto/server.py
aioslimproto/util.py
aioslimproto/visualisation.py
aioslimproto/volume.py
aioslimproto/font/Arial.ttf
aioslimproto/font/DejaVu-Sans-Bold-Oblique.ttf
aioslimproto/font/DejaVu-Sans-Bold.ttf
aioslimproto/font/DejaVu-Sans-Condensed-Bold-Oblique.ttf
aioslimproto/font/DejaVu-Sans-Condensed-Bold.ttf
aioslimproto/font/DejaVu-Sans-Condensed-Oblique.ttf
aioslimproto/font/DejaVu-Sans-Condensed.ttf
aioslimproto/font/DejaVu-Sans-ExtraLight.ttf
aioslimproto/font/DejaVu-Sans-Mono-Bold-Oblique.ttf
aioslimproto/font/DejaVu-Sans-Mono-Bold.ttf
aioslimproto/font/DejaVu-Sans-Mono-Oblique.ttf
aioslimproto/font/DejaVu-Sans-Mono.ttf
aioslimproto/font/DejaVu-Sans-Oblique.ttf
aioslimproto/font/DejaVu-Sans.ttf
aioslimproto/font/Gidole-Regular.ttf
aioslimproto-3.1.2.dist-info/licenses/LICENSE
aioslimproto-3.1.2.dist-info/METADATA
aioslimproto-3.1.2.dist-info/WHEEL
aioslimproto-3.1.2.dist-info/top_level.txt
aioslimproto-3.1.2.dist-info/RECORD
