Metadata-Version: 2.4
Name: aioslimproto
Version: 3.1.2
Summary: Python module to talk to Logitech Squeezebox players directly (without Logitech server).
Author-email: Marcel van der Veldt <marcelveldt@users.noreply.github.com>
License: Apache-2.0
Platform: any
Classifier: Environment :: Console
Classifier: Programming Language :: Python :: 3.11
Classifier: Programming Language :: Python :: 3.12
Requires-Python: >=3.11
License-File: LICENSE
Requires-Dist: aiohttp>=3.9.2
Requires-Dist: pillow
Provides-Extra: test
Requires-Dist: codespell==2.4.1; extra == "test"
Requires-Dist: isort==6.0.1; extra == "test"
Requires-Dist: mypy==1.18.2; extra == "test"
Requires-Dist: pre-commit==4.3.0; extra == "test"
Requires-Dist: pre-commit-hooks==6.0.0; extra == "test"
Requires-Dist: pytest==8.4.1; extra == "test"
Requires-Dist: pytest-asyncio==1.2.0; extra == "test"
Requires-Dist: pytest-aiohttp==1.1.0; extra == "test"
Requires-Dist: pytest-cov==7.0.0; extra == "test"
Requires-Dist: ruff==0.12.8; extra == "test"
Requires-Dist: safety==3.6.2; extra == "test"
Requires-Dist: tomli==2.2.1; extra == "test"
Dynamic: license-file
